{
  "updated": "2026-07-18",
  "positions": [
    {
      "ticker": "SPRB",
      "company": "Spruce Biosciences, Inc.",
      "folder": "companies/SPRB",
      "thesis": "Sole ERT for MPS IIIB (Sanfilippo B), BLA filing guided Q4-26. Bottom-up rNPV/DCF below current price; upside case depends on peer-multiple re-rating or BioMarin buyout.",
      "price": 43.54,
      "bear": 19,
      "mid": 51,
      "bull": 165,
      "catalyst": "BLA filing",
      "catdate": "2026-10-01",
      "status": "active",
      "questions": "Confirm diagnosed patient count via KOL; confirm exact BioMarin royalty rate; watch confirmatory-trial power given modest effect size.",
      "updated": "2026-07-18"
    }
  ]
}
